stix2patterns_translator/__init__.py
stix2patterns_translator/errors.py
stix2patterns_translator/parser.py
stix2patterns_translator/pattern_objects.py
stix2patterns_translator/translator.py
stix2patterns_translator/web_api.py
stix2patterns_translator/data_models/__init__.py
stix2patterns_translator/data_models/base.py
stix2patterns_translator/data_models/car.py
stix2patterns_translator/data_models/cim.py
stix2patterns_translator/grammar/STIXPatternLexer.py
stix2patterns_translator/grammar/STIXPatternListener.py
stix2patterns_translator/grammar/STIXPatternParser.py
stix2patterns_translator/grammar/STIXPatternVisitor.py
stix2patterns_translator/grammar/__init__.py
stix2patterns_translator/search_platforms/__init__.py
stix2patterns_translator/search_platforms/elastic_query_string.py
stix2patterns_translator/search_platforms/splunk_search.py
stix2patterns_translator/search_platforms/splunk/__init__.py
stix2patterns_translator/search_platforms/splunk/encoders.py
stix2patterns_translator/search_platforms/splunk/object_scopers.py
stix_pattern_translator-0.2.0.dist-info/DESCRIPTION.rst
stix_pattern_translator-0.2.0.dist-info/METADATA
stix_pattern_translator-0.2.0.dist-info/RECORD
stix_pattern_translator-0.2.0.dist-info/WHEEL
stix_pattern_translator-0.2.0.dist-info/entry_points.txt
stix_pattern_translator-0.2.0.dist-info/metadata.json
stix_pattern_translator-0.2.0.dist-info/top_level.txt
