Metadata-Version: 2.0
Name: stix-pattern-translator
Version: 0.2.0
Summary: A translator to convert STIX2 patterns into other search platforms (e.g., ElasticSearch) and data models (e.g., CIM)
Home-page: https://github.com/mitre/stix2patterns_translator
Author: The MITRE Corporation
Author-email: hfoster@mitre.org
License: Apache License 2.0
Keywords: stix cybersecurity analytics
Platform: UNKNOWN
Classifier: Development Status :: 3 - Alpha
Classifier: Intended Audience :: Developers
Classifier: Topic :: Security
Classifier: License :: OSI Approved :: Apache Software License
Classifier: Programming Language :: Python :: 3
Classifier: Programming Language :: Python :: 3.5
Classifier: Programming Language :: Python :: 3.6
Provides-Extra: dev
Provides-Extra: web
Requires-Dist: antlr4-python3-runtime
Requires-Dist: python-dateutil
Provides-Extra: dev
Requires-Dist: pytest; extra == 'dev'
Requires-Dist: tox; extra == 'dev'
Requires-Dist: flask; extra == 'dev'
Requires-Dist: requests; extra == 'dev'
Provides-Extra: web
Requires-Dist: flask; extra == 'web'
